hddm_r.cp39-win32.pyd
hddm_r/rest.xml
hddm_r-2.0.21.dist-info/LICENSE
hddm_r-2.0.21.dist-info/METADATA
hddm_r-2.0.21.dist-info/WHEEL
hddm_r-2.0.21.dist-info/top_level.txt
hddm_r-2.0.21.dist-info/RECORD
