Metadata-Version: 2.1
Name: hddm-r
Version: 2.0.21
Summary: i/o module for GlueX reconstructed events
Home-page: https://github.com/rjones30/hddm_r
Author: Richard T. Jones
License: UNKNOWN
Platform: UNKNOWN
Classifier: Programming Language :: Python :: 3
Classifier: License :: OSI Approved :: MIT License
Classifier: Operating System :: OS Independent
Requires-Python: >=3.6
License-File: LICENSE
